mopidy_discord/__init__.py
mopidy_discord/discordthread.py
mopidy_discord/ext.conf
mopidy_discord/frontend.py
Mopidy_Discord-0.1.1.dist-info/LICENSE
Mopidy_Discord-0.1.1.dist-info/METADATA
Mopidy_Discord-0.1.1.dist-info/WHEEL
Mopidy_Discord-0.1.1.dist-info/entry_points.txt
Mopidy_Discord-0.1.1.dist-info/top_level.txt
Mopidy_Discord-0.1.1.dist-info/RECORD
